releaseherald/__init__.py
releaseherald/configuration.py
releaseherald/main.py
releaseherald/version.py
releaseherald/plugins/__init__.py
releaseherald/plugins/base.py
releaseherald/plugins/hookspecs.py
releaseherald/plugins/interface.py
releaseherald/plugins/latest_filter.py
releaseherald/plugins/manager.py
releaseherald/plugins/metadata_extractor.py
releaseherald/plugins/plugin_config.py
releaseherald/plugins/submodules.py
releaseherald/templates/__init__.py
releaseherald/templates/news.rst
releaseherald-0.1.0.dist-info/LICENSE
releaseherald-0.1.0.dist-info/METADATA
releaseherald-0.1.0.dist-info/WHEEL
releaseherald-0.1.0.dist-info/entry_points.txt
releaseherald-0.1.0.dist-info/top_level.txt
releaseherald-0.1.0.dist-info/RECORD
