Metadata-Version: 2.1
Name: releaseherald
Version: 0.1.0
Summary: Git tag based release note generator
Author-email: Morgan Stanley <eti-testplan@morganstanley.com>
License: Apache License
Project-URL: Homepage, https://github.com/morganstanley/releaseherald
Project-URL: Repository, https://github.com/morganstanley/releaseherald.git
Keywords: releasenotes,release,whatsnew,git
Classifier: Development Status :: 4 - Beta
Classifier: Intended Audience :: Developers
Classifier: License :: OSI Approved :: Apache Software License
Classifier: Programming Language :: Python :: 3
Classifier: Programming Language :: Python :: 3.7
Classifier: Programming Language :: Python :: 3.8
Classifier: Programming Language :: Python :: 3.9
Classifier: Programming Language :: Python :: 3.10
Classifier: Programming Language :: Python :: 3.11
Classifier: Topic :: Software Development :: Version Control :: Git
Requires-Python: >=3.7
License-File: LICENSE
Requires-Dist: boltons
Requires-Dist: click
Requires-Dist: GitPython
Requires-Dist: Jinja2
Requires-Dist: parse
Requires-Dist: toml
Requires-Dist: typing-extensions
Requires-Dist: pydantic (<2.0)
Requires-Dist: pluggy
Provides-Extra: dev
Requires-Dist: black (~=23.3) ; extra == 'dev'
Requires-Dist: mypy ; extra == 'dev'
Requires-Dist: types-toml ; extra == 'dev'
Requires-Dist: ruff ; extra == 'dev'
Requires-Dist: pytest ; extra == 'dev'
Requires-Dist: doit ; extra == 'dev'
Provides-Extra: docs
Requires-Dist: mkdocs ; extra == 'docs'
Requires-Dist: mkdocs-click ; extra == 'docs'
Requires-Dist: mkdocs-mermaid2-plugin ; extra == 'docs'
Requires-Dist: mkdocs-awesome-pages-plugin ; extra == 'docs'
Requires-Dist: mkdocstrings[python] ; extra == 'docs'
